sentry_dingding/__init__.py
sentry_dingding/forms.py
sentry_dingding/plugin.py
sentry_stack_dingding-1.0.22.dist-info/METADATA
sentry_stack_dingding-1.0.22.dist-info/WHEEL
sentry_stack_dingding-1.0.22.dist-info/entry_points.txt
sentry_stack_dingding-1.0.22.dist-info/top_level.txt
sentry_stack_dingding-1.0.22.dist-info/RECORD
