Metadata-Version: 2.1
Name: sentry-stack-dingding
Version: 1.0.22
Summary: A Sentry extension which send errors stats to DingDing
Home-page: https://github.com/wilsonloo/sentry-stack-dingding.git
Author: wilson-loo
Author-email: 614231319@qq.com
License: MIT
Keywords: sentry stack dingding
Classifier: Programming Language :: Python :: 2.7
Classifier: License :: OSI Approved :: MIT License
Requires-Dist: requests
Requires-Dist: sentry (>=9.0.0)
